Workbook

Sheet 1. Master Item List
A1: ACHIRA LABS — MASTER ITEM LIST (Source: Zoho + ARN Assignment)
A2: ARN | B2: Zoho Item ID | C2: Item Name | D2: Dept | E2: Sub-Category | F2: Zoho Category | G2: SKU | H2: Brand | I2: Unit | J2: Purchase Price | K2: Stock On Hand | L2: Reorder Level | M2: Warehouse / Location | N2: Preferred Vendor | O2: Status | P2: Product Type | Q2: Last Updated | R2: Notes
A3: ACH-RD-CH-0001 | B3: 1.22e+18 | C3: A1653-ALBUMIN FROM HUMAN SERUM | D3: RD | E3: CH | F3: A1653-ALBUMIN FROM HUMAN SERUM | H3: Sigma | I3: ug | J3: INR 0.014 | K3: 500000 | M3: 2-8 Fridge R_D Section | O3: Inactive | P3: goods
A4: ACH-RD-CH-0002 | B4: 1.22e+18 | C4: 2FSH2 F2 Anti FSH Beta Chain | D4: RD | E4: CH | F4: Assay Development | H4: Hytest | I4: ug | J4: INR 9.435 | K4: 14350 | M4: 2-8 Fridge R_D Section | O4: Active | P4: goods
A5: ACH-RD-CH-0003 | B5: 1.22e+18 | C5: SM01-0050-Assay Diluent - Protein Free | D5: RD | E5: CH | F5: LF Assay | H5: Surmodics | J5: INR 0.16758 | K5: 0 | M5: 2-8 Fridge R_D Section | N5: Biogenuix Medsystems Pvt. Ltd. | O5: Active | P5: goods
A6: ACH-EN-EL-0001 | B6: 1.22e+18 | C6: 131050- Antibody Stabilizer | D6: EN | E6: EL | F6: 131050- Antibody Stabilizer | H6: Candoor | I6: ul | J6: INR 0.50 | K6: 0 | M6: 2-8 Fridge R_D Section | N6: BioAzure Technologies Pvt. Ltd. | O6: Active | P6: goods
A7: ACH-RD-CH-0004 | B7: 1.22e+18 | C7: A3699-Acrylamide/bis-Acrylamide | D7: RD | E7: CH | F7: A3699-Acrylamide/bis-Acrylamide | H7: Sigma | I7: ul | J7: INR 0.06405 | K7: 0 | M7: 2-8 Fridge R_D Section | N7: Sigma Aldrich Chemicals Pvt Ltd | O7: Active | P7: goods
A8: ACH-RD-CH-0005 | B8: 1.22e+18 | C8: A2281-Amikacan Sulfate | D8: RD | E8: CH | F8: A2281-Amikacan Sulfate | H8: TCI | I8: mg | J8: INR 0.074 | K8: 50000 | M8: 2-8 Fridge R_D Section | O8: Active | P8: goods
A9: ACH-RD-CH-0006 | B9: 1.22e+18 | C9: A2092-Anmpicillin Tridydrate | D9: RD | E9: CH | F9: A2092-Anmpicillin Tridydrate | H9: TCI | I9: mg | J9: INR 0.74 | K9: 5000 | M9: 2-8 Fridge R_D Section | N9: Scientific & Allied Products | O9: Active | P9: goods
A10: ACH-RD-CH-0007 | B10: 1.22e+18 | C10: 29281-8 - Acrylsaure(2-Hydroxy Ethyl Ester) | D10: RD | E10: CH | F10: 29281-8 - Acrylsaure(2-Hydroxy Ethyl Ester) | H10: Sigma | I10: ul | J10: INR 0.01 | K10: 0 | M10: 2-8 Fridge R_D Section | N10: Sigma Aldrich Chemicals Pvt Ltd | O10: Active | P10: goods
A11: ACH-RD-AB-0001 | B11: 1.22e+18 | C11: 100066 -Anti-h Alpha Subunit - 6601-SPR5 | D11: RD | E11: AB | F11: Assay Development | H11: Medix | I11: ug | J11: INR 6.60 | K11: 2600 | M11: 2-8 Fridge R_D Section | O11: Active | P11: goods
A12: ACH-GN-IT-0001 | B12: 1.22e+18 | C12: NVIDIA RTX A4000 - 16GB CARD | D12: GN | E12: IT | F12: Capex | H12: NVIDIA | I12: No | J12: INR 70400.00 | K12: 1 | O12: Active | P12: goods
A13: ACH-RD-CH-0008 | B13: 1.22e+18 | C13: A3059-Albumin from Bovine Serum | D13: RD | E13: CH | F13: A3059-Albumin from Bovine Serum | H13: Sigma | I13: mg | J13: INR 0.53736 | K13: 0 | M13: 2-8 Fridge R_D Section | N13: Sigma Aldrich Chemicals Pvt Ltd | O13: Active | P13: goods
A14: ACH-RD-CH-0009 | B14: 1.22e+18 | C14: 338818 - Ammonium Hydroxide Solution | D14: RD | E14: CH | F14: 338818 - Ammonium Hydroxide Solution | H14: Sigma | I14: ul | J14: INR 0.068153 | K14: 0 | M14: 2-8 Fridge R_D Section | O14: Active | P14: goods
A15: ACH-RD-CH-0010 | B15: 1.22e+18 | C15: A7906-Bovine Serum Albumin | D15: RD | E15: CH | F15: A7906-Bovine Serum Albumin | H15: Sigma | I15: mg | J15: INR 0.83326 | K15: 7980 | M15: 2-8 Fridge R_D Section | O15: Active | P15: goods
A16: ACH-RD-FL-0001 | B16: 1.22e+18 | C16: B4501-Biotin 99% (HPLC) Liophilized Powder | D16: RD | E16: FL | F16: B4501-Biotin 99% (HPLC) Liophilized Powder | H16: Sigma | I16: ug | J16: INR 0.0208 | K16: 100000 | M16: 2-8 Fridge R_D Section | N16: Sigma Aldrich Chemicals Pvt Ltd | O16: Active | P16: goods
A17: ACH-RD-CH-0011 | B17: 1.22e+18 | C17: 621650500501730-BSA (Bovine Serum Albumin) | D17: RD | E17: CH | F17: 621650500501730-BSA (Bovine Serum Albumin) | H17: Sigma | I17: mg | J17: INR 1.00 | K17: 0 | M17: 2-8 Fridge R_D Section | N17: Sigma Aldrich Chemicals Pvt Ltd | O17: Active | P17: goods
A18: ACH-RD-CH-0012 | B18: 1.22e+18 | C18: A2153 - Bovine Serum Albumin | D18: RD | E18: CH | F18: A2153 - Bovine Serum Albumin | H18: Sigma | I18: mg | J18: INR 0.57792 | K18: 0 | M18: 2-8 Fridge R_D Section | N18: Sigma Aldrich Chemicals Pvt Ltd | O18: Active | P18: goods
A19: ACH-RD-CH-0013 | B19: 1.22e+18 | C19: 411744- 1,4-Butanediol Diacrylate | D19: RD | E19: CH | F19: 411744- 1,4-Butanediol Diacrylate | H19: Sigma | I19: ul | J19: INR 0.03994 | K19: 0 | M19: 2-8 Fridge R_D Section | N19: Sigma Aldrich Chemicals Pvt Ltd | O19: Active | P19: goods
A20: ACH-RD-CH-0014 | B20: 1.22e+18 | C20: MB083-Bovin Serum Albumin | D20: RD | E20: CH | F20: MB083-Bovin Serum Albumin | H20: Himedia | I20: mg | J20: INR 0.07448 | K20: 251357 | M20: 2-8 Fridge R_D Section | N20: Vasa Scientific Company | O20: Active | P20: goods
A21: ACH-RD-CH-0015 | B21: 1.22e+18 | C21: B6916-Bradford Reagent | D21: RD | E21: CH | F21: B6916-Bradford Reagent | H21: Sigma | I21: ul | J21: INR 0.015 | K21: 480000 | M21: 2-8 Fridge R_D Section | N21: Sigma Aldrich Chemicals Pvt Ltd | O21: Active | P21: goods
A22: ACH-RD-CH-0016 | B22: 1.22e+18 | C22: B684970 - 2-Bromo 17 beta estradiol | D22: RD | E22: CH | F22: B684970 - 2-Bromo 17 beta estradiol | H22: TRC | I22: ug | J22: INR 0.15 | K22: 0 | M22: 2-8 Fridge R_D Section | N22: Toronto Research Chemicals, Inc. | O22: Active | P22: goods
A23: ACH-RD-CH-0017 | B23: 1.22e+18 | C23: C1063 - Chorionic Gonadotropin, Human | D23: RD | E23: CH | F23: C1063 - Chorionic Gonadotropin, Human | H23: Sigma | I23: ul | J23: INR 0.674399 | K23: 0 | M23: 2-8 Fridge R_D Section | N23: Sigma Aldrich Chemicals Pvt Ltd | O23: Active | P23: goods
A24: ACH-RD-KT-0001 | B24: 1.22e+18 | C24: Chikungunya IGM ELISA - MicroLisa | D24: RD | E24: KT | F24: Chikungunya IGM ELISA - MicroLisa | H24: J Mitra | I24: Test | J24: INR 140.625 | K24: 0 | M24: 2-8 Fridge R_D Section | N24: Aspire Diagnoline Pvt. Ltd | O24: Active | P24: goods
A25: ACH-RD-FL-0002 | B25: 1.22e+18 | C25: CdTe Quantum Dots | D25: RD | E25: FL | F25: CdTe Quantum Dots | H25: Plasmachem | I25: ug | J25: INR 0.741 | K25: 7000 | M25: 2-8 Fridge R_D Section | N25: Plasmachem GmbH | O25: Active | P25: goods
A26: ACH-RD-KT-0002 | B26: 1.22e+18 | C26: Dengue IGM ELISA - MicroLisa | D26: RD | E26: KT | F26: Dengue IGM ELISA - MicroLisa | H26: J Mitra | I26: Test | J26: INR 84.895 | K26: 0 | M26: 2-8 Fridge R_D Section | N26: Aspire Diagnoline Pvt. Ltd | O26: Active | P26: goods
A27: ACH-RD-KT-0003 | B27: 1.22e+18 | C27: Dengue IGG ELISA-MicroLisa | D27: RD | E27: KT | F27: Dengue IGG ELISA-MicroLisa | H27: J Mitra | I27: Test | J27: INR 84.895 | K27: 0 | M27: 2-8 Fridge R_D Section | N27: Aspire Diagnoline Pvt. Ltd | O27: Active | P27: goods
... A29: ACH-RD-CH-0019 | B29: 1.22e+18 | C29: D0632-DL-Dithiothreitol | D29: RD | E29: CH | F29: D0632-DL-Dithiothreitol | H29: Sigma | I29: mg | J29: INR 1.82 | K29: 0 | M29: 2-8 Fridge R_D Section | N29: Sigma Aldrich Chemicals Pvt Ltd | O29: Active | P29: goods
A30: ACH-RD-AB-0002 | B30: 1.22e+18 | C30: 375.1% -Carboxylate -1.5 Mmol/g | D30: RD | E30: AB | F30: 375.1% -Carboxylate -1.5 Mmol/g | H30: Betulium | I30: ul | J30: INR 0.0069 | K30: 0 | M30: 2-8 Fridge R_D Section | O30: Active | P30: goods
A31: ACH-RD-FL-0003 | B31: 1.22e+18 | C31: CMS095 - D-Biotin | D31: RD | E31: FL | F31: CMS095 - D-Biotin | H31: Himedia | I31: mg | J31: INR 2.65 | K31: 0 | M31: 2-8 Fridge R_D Section | O31: Active | P31: goods
A32: ACH-RD-FL-0004 | B32: 1.22e+18 | C32: DY-647P4-NHS-Easter | D32: RD | E32: FL | F32: DY-647P4-NHS-Easter | H32: Dyomics | I32: ug | J32: INR 11.76 | K32: 33000 | M32: 2-8 Fridge R_D Section | N32: Dyomics GmbH | O32: Active | P32: goods
A33: ACH-RD-FL-0005 | B33: 1.22e+18 | C33: DY-647P4-NHS-Easter | D33: RD | E33: FL | F33: DY-647P4-NHS-Easter | H33: Dyomics | I33: ug | J33: INR 11.76 | K33: 33000 | M33: -20 Fridge R_D Section | N33: Dyomics GmbH | O33: Active | P33: goods
A34: ACH-RD-FL-0006 | B34: 1.22e+18 | C34: DY-634-NHS-Easter | D34: RD | E34: FL | F34: DY-634-NHS-Easter | H34: Dyomics | I34: ug | J34: INR 8.925 | K34: 0 | M34: 2-8 Fridge R_D Section | N34: Dyomics GmbH | O34: Active | P34: goods
A35: ACH-RD-FL-0007 | B35: 1.22e+18 | C35: DY-649-NHS-Easter | D35: RD | E35: FL | F35: DY-649-NHS-Easter | H35: Dyomics | I35: ug | J35: INR 8.925 | K35: 0 | M35: 2-8 Fridge R_D Section | N35: Dyomics GmbH | O35: Active | P35: goods
A36: ACH-RD-FL-0008 | B36: 1.22e+18 | C36: DY-649P1-NHS-Easter | D36: RD | E36: FL | F36: DY-649P1-NHS-Easter | H36: Dyomics | I36: ug | J36: INR 8.925 | K36: 0 | M36: 2-8 Fridge R_D Section | O36: Active | P36: goods
A37: ACH-RD-FL-0009 | B37: 1.22e+18 | C37: DY-651-Amin | D37: RD | E37: FL | F37: DY-651-Amin | H37: Dyomics | I37: ug | J37: INR 8.925 | K37: 0 | M37: 2-8 Fridge R_D Section | N37: Dyomics GmbH | O37: Active | P37: goods
A38: ACH-RD-FL-0010 | B38: 1.22e+18 | C38: DY-654-Amin | D38: RD | E38: FL | F38: DY-654-Amin | H38: Dyomics | I38: ug | J38: INR 8.925 | K38: 0 | M38: 2-8 Fridge R_D Section | O38: Active | P38: goods
A39: ACH-RD-FL-0011 | B39: 1.22e+18 | C39: DY-634-Amin | D39: RD | E39: FL | F39: DY-634-Amin | H39: Dyomics | I39: ug | J39: INR 8.925 | K39: 0 | M39: 2-8 Fridge R_D Section | N39: Dyomics GmbH | O39: Active | P39: goods
A40: ACH-RD-FL-0012 | B40: 1.22e+18 | C40: DY-654-NHS-Easter | D40: RD | E40: FL | F40: DY-654-NHS-Easter | H40: Dyomics | I40: ug | J40: INR 8.925 | K40: 0 | M40: 2-8 Fridge R_D Section | N40: Dyomics GmbH | O40: Active | P40: goods
A41: ACH-RD-FL-0013 | B41: 1.22e+18 | C41: DY-634-Maleimide | D41: RD | E41: FL | F41: DY-634-Maleimide | H41: Dyomics | I41: ug | J41: INR 8.925 | K41: 0 | M41: 2-8 Fridge R_D Section | N41: Dyomics GmbH | O41: Active | P41: goods
A42: ACH-RD-CH-0020 | B42: 1.22e+18 | C42: E5630-B-Estradiol - 6()-Carboxmethtl) oxime-BSA | D42: RD | E42: CH | F42: Assay Development | H42: Sigma | I42: ug | J42: INR 3.75 | K42: 2000 | M42: 2-8 Fridge R_D Section | N42: Sigma Aldrich Chemicals Pvt Ltd | O42: Active | P42: goods
A43: ACH-RD-FL-0014 | B43: 1.22e+18 | C43: FD250S-Fluorescein isothiocyanate dextran | D43: RD | E43: FL | F43: FD250S-Fluorescein isothiocyanate dextran | H43: Sigma | I43: ug | J43: INR 0.038 | K43: 10 | M43: 2-8 Fridge R_D Section | N43: Sigma Aldrich Chemicals Pvt Ltd | O43: Active | P43: goods
A44: ACH-RD-FL-0015 | B44: 1.22e+18 | C44: FD2000S - Fluorescein isothiocyanate dextran | D44: RD | E44: FL | F44: FD2000S - Fluorescein isothiocyanate dextran | H44: Sigma | I44: ug | J44: INR 0.038 | K44: 125000 | M44: 2-8 Fridge R_D Section | N44: Sigma Aldrich Chemicals Pvt Ltd | O44: Active | P44: goods
A45: ACH-RD-FL-0016 | B45: 1.22e+18 | C45: FD500S -Fluorescein isothiocyanate dextran | D45: RD | E45: FL | F45: FD500S -Fluorescein isothiocyanate dextran | H45: Sigma | I45: ug | J45: INR 0.038 | K45: 9800 | M45: 2-8 Fridge R_D Section | N45: Sigma Aldrich Chemicals Pvt Ltd | O45: Active | P45: goods
A46: ACH-RD-FL-0017 | B46: 1.22e+18 | C46: 19773-Fluoresbrite BB Carboxylate Microspheres 0.05um | D46: RD | E46: FL | F46: 19773-Fluoresbrite BB Carboxylate Microspheres 0.05um | H46: Polyscience | I46: ul | J46: INR 4.8048 | K46: 0 | M46: 2-8 Fridge R_D Section | N46: Genomid Life Science | O46: Active | P46: goods
A47: ACH-RD-FL-0018 | B47: 1.22e+18 | C47: 16661-Fluoresbrite YG Carboxylate Microspheres 0.05um | D47: RD | E47: FL | F47: 16661-Fluoresbrite YG Carboxylate Microspheres 0.05um | H47: Polyscience | I47: ul | J47: INR 4.7938 | K47: 0 | M47: 2-8 Fridge R_D Section | N47: Genomid Life Science | O47: Active | P47: goods
A48: ACH-RD-AB-0003 | B48: 1.22e+18 | C48: 100022-Anti-H LH-5304-SP-5 | D48: RD | E48: AB | F48: Assay Development | H48: Medix | I48: ug | J48: INR 5.192 | K48: 9477 | M48: 2-8 Fridge R_D Section | O48: Active | P48: goods
A49: ACH-RD-CH-0021 | B49: 1.22e+18 | C49: 22586-DSP Dithiobis (succinimidylpropionate) | D49: RD | E49: CH | F49: 22586-DSP Dithiobis (succinimidylpropionate) | H49: Thermo | I49: ug | J49: INR 0.3025 | K49: 0 | M49: 2-8 Fridge R_D Section | O49: Active | P49: goods
A50: ACH-RD-CH-0022 | B50: 1.22e+18 | C50: ML014 - 0.5 M EDTA pH 8.0 Used in various Molecular Biology Applications | D50: RD | E50: CH | F50: ML014 - 0.5 M EDTA pH 8.0 Used in various Molecular Biology Applications | H50: Himedia | I50: ul | J50: INR 0.01 | K50: 500000 | M50: 2-8 Fridge R_D Section | O50: Active | P50: goods
A51: ACH-RD-CH-0023 | B51: 1.22e+18 | C51: ML014 - 0.5 M EDTA pH 8.0 Used in various Molecular Biology Applications | D51: RD | E51: CH | F51: ML014 - 0.5 M EDTA pH 8.0 Used in various Molecular Biology Applications | H51: Himedia | I51: ul | J51: INR 0.01 | K51: 500000 | M51: Room Temperature R_D Section | O51: Active | P51: goods
A52: ACH-RD-CH-0024 | B52: 1.22e+18 | C52: F1141 - Fibronectin 0.1% Solution from Bovine Plasa | D52: RD | E52: CH | F52: F1141 - Fibronectin 0.1% Solution from Bovine Plasa | H52: Sigma | I52: ug | J52: INR 12.61 | K52: 0 | M52: 2-8 Fridge R_D Section | N52: Sigma Aldrich Chemicals Pvt Ltd | O52: Active | P52: goods
A53: ACH-RD-CH-0025 | B53: 1.22e+18 | C53: Fluoro-Max - Carboxylate-Modified Died Macroparticles | D53: RD | E53: CH | F53: Fluoro-Max - Carboxylate-Modified Died Macroparticles | H53: Thermo | I53: ul | J53: INR 1.00 | K53: 0 | M53: 2-8 Fridge R_D Section | O53: Active | P53: goods
A54: ACH-RD-AB-0004 | B54: 1.22e+18 | C54: Fibrinogen Reagent- Thrombine | D54: RD | E54: AB | F54: Fibrinogen Reagent- Thrombine | H54: Technoclone | I54: ul | J54: INR 1.00 | K54: 0 | M54: 2-8 Fridge R_D Section | O54: Active | P54: goods
A55: ACH-RD-FL-0019 | B55: 1.22e+18 | C55: GSXR150 - Bioready Gold Nanoshells | D55: RD | E55: FL | F55: LF Assay | H55: Nano Composix | I55: ul | J55: INR 4.20 | K55: 0 | M55: 2-8 Fridge R_D Section | N55: Amplicon Biotech | O55: Active | P55: goods
A56: ACH-RD-CH-0026 | B56: 1.22e+18 | C56: H7379 Hemoglobin Human | D56: RD | E56: CH | F56: H7379 Hemoglobin Human | H56: Sigma | I56: mg | J56: INR 5.68 | K56: 1000 | M56: 2-8 Fridge R_D Section | N56: Sigma Aldrich Chemicals Pvt Ltd | O56: Active | P56: goods
A57: ACH-RD-CH-0027 | B57: 1.22e+18 | C57: 467804-Hydroxylamine Solution | D57: RD | E57: CH | F57: 467804-Hydroxylamine Solution | H57: Sigma | I57: ul | J57: INR 0.5328 | K57: 3000 | M57: 2-8 Fridge R_D Section | N57: Sigma Aldrich Chemicals Pvt Ltd | O57: Active | P57: goods
A58: ACH-RD-AB-0005 | B58: 1.22e+18 | C58: MBS173396 Human Serum Albumin - Protease Free | D58: RD | E58: AB | F58: MBS173396 Human Serum Albumin - Protease Free | H58: MyBiosource | I58: mg | J58: INR 11.20 | K58: 0 | M58: 2-8 Fridge R_D Section | O58: Active | P58: goods
A59: ACH-RD-CH-0028 | B59: 1.22e+18 | C59: 477028 - Hydroxyenthel methacrylate | D59: RD | E59: CH | F59: 477028 - Hydroxyenthel methacrylate | H59: Sigma | I59: ul | J59: INR 0.17 | K59: 0 | M59: 2-8 Fridge R_D Section | N59: Sigma Aldrich Chemicals Pvt Ltd | O59: Active | P59: goods
A60: ACH-RD-CH-0029 | B60: 1.22e+18 | C60: G0383- Gentamicin Sulphate | D60: RD | E60: CH | F60: G0383- Gentamicin Sulphate | H60: TCI | I60: mg | J60: INR 5.10 | K60: 1000 | M60: 2-8 Fridge R_D Section | O60: Active | P60: goods
A61: ACH-RD-CH-0030 | B61: 1.22e+18 | C61: 254169 - Gold (III) Chloride Hydrate | D61: RD | E61: CH | F61: 254169 - Gold (III) Chloride Hydrate | H61: Sigma | I61: ug | J61: INR 1.76 | K61: 0 | M61: 2-8 Fridge R_D Section | N61: Sigma Aldrich Chemicals Pvt Ltd | O61: Active | P61: goods
A62: ACH-RD-AB-0006 | B62: 1.22e+18 | C62: 100011 - Anti-HCG - 5014 - SPTN-5 | D62: RD | E62: AB | F62: Assay Development | H62: Medix | I62: ug | J62: INR 2.25 | K62: 2490 | M62: 2-8 Fridge R_D Section | N62: Medix | O62: Active | P62: goods
A63: ACH-RD-AB-0007 | B63: 1.22e+18 | C63: P01-29342 -Anti Hemoglobin Polyclonal Antibody | D63: RD | E63: AB | F63: P01-29342 -Anti Hemoglobin Polyclonal Antibody | H63: Thermo | I63: ug | J63: INR 34.48 | K63: 0 | M63: 2-8 Fridge R_D Section | O63: Active | P63: goods
A64: ACH-RD-AB-0008 | B64: 1.22e+18 | C64: Anti-HCG 2H8 Mab F1 | D64: RD | E64: AB | F64: Anti-HCG 2H8 Mab F1 | H64: Hytest | I64: ul | J64: INR 3.50 | K64: 0 | M64: 2-8 Fridge R_D Section | N64: HyTest Ltd | O64: Active | P64: goods
A65: ACH-RD-CH-0031 | B65: 1.22e+18 | C65: H3375-HEPES | D65: RD | E65: CH | F65: H3375-HEPES | H65: Sigma | I65: mg | J65: INR 0.175 | K65: 10000 | M65: 2-8 Fridge R_D Section | N65: Sigma Aldrich Chemicals Pvt Ltd | O65: Active | P65: goods
A66: ACH-RD-CH-0032 | B66: 1.22e+18 | C66: 107689 - Hexadimethrine bromide | D66: RD | E66: CH | F66: 107689 - Hexadimethrine bromide | H66: Sigma | I66: mg | J66: INR 0.60 | K66: 0 | M66: 2-8 Fridge R_D Section | N66: Sigma Aldrich Chemicals Pvt Ltd | O66: Active | P66: goods
A67: ACH-RD-CH-0033 | B67: 1.22e+18 | C67: 477028-2-Hydroxyethyl methacrylate 99% | D67: RD | E67: CH | F67: 477028-2-Hydroxyethyl methacrylate 99% | H67: Sigma | I67: ul | J67: INR 0.17 | K67: 0 | M67: 2-8 Fridge R_D Section | N67: Sigma Aldrich Chemicals Pvt Ltd | O67: Active | P67: goods
A68: ACH-RD-CH-0034 | B68: 1.22e+18 | C68: 308633 - 2-Hydroxyethyl Cellulose | D68: RD | E68: CH | F68: 308633 - 2-Hydroxyethyl Cellulose | H68: Sigma | I68: mg | J68: INR 0.16 | K68: 0 | M68: 2-8 Fridge R_D Section | N68: Sigma Aldrich Chemicals Pvt Ltd | O68: Active | P68: goods
A69: ACH-RD-CH-0035 | B69: 1.22e+18 | C69: 475807 - Glycerol 1,3-diglycerolate diacrylate | D69: RD | E69: CH | F69: 475807 - Glycerol 1,3-diglycerolate diacrylate | H69: Sigma | I69: ul | J69: INR 0.03 | K69: 0 | M69: 2-8 Fridge R_D Section | N69: Sigma Aldrich Chemicals Pvt Ltd | O69: Active | P69: goods
A70: ACH-RD-CH-0036 | B70: 1.22e+18 | C70: I6256-2-Iminothiolane hydrochloride | D70: RD | E70: CH | F70: I6256-2-Iminothiolane hydrochloride | H70: Sigma | I70: ug | J70: INR 0.05 | K70: 0 | M70: 2-8 Fridge R_D Section | N70: Sigma Aldrich Chemicals Pvt Ltd | O70: Active | P70: goods
A71: ACH-RD-CH-0037 | B71: 1.22e+18 | C71: I6758 - Isopropyl B-D-1thiogalactopyranoside | D71: RD | E71: CH | F71: I6758 - Isopropyl B-D-1thiogalactopyranoside | H71: Sigma | I71: mg | J71: INR 6.49 | K71: 0 | M71: 2-8 Fridge R_D Section | N71: Sigma Aldrich Chemicals Pvt Ltd | O71: Active | P71: goods
A72: ACH-RD-CH-0038 | B72: 1.22e+18 | C72: 33015 - ImmunoPure AMCA - Hydrazide | D72: RD | E72: CH | F72: 33015 - ImmunoPure AMCA - Hydrazide | H72: Thermo | I72: ug | J72: INR 0.21 | K72: 0 | M72: 2-8 Fridge R_D Section | O72: Active | P72: goods
A73: ACH-RD-AB-0009 | B73: 1.22e+18 | C73: I5381 - IGG from Mouse Serum | D73: RD | E73: AB | F73: I5381 - IGG from Mouse Serum | H73: Sigma | I73: ug | J73: INR 3.90 | K73: 0 | M73: 2-8 Fridge R_D Section | N73: Sigma Aldrich Chemicals Pvt Ltd | O73: Active | P73: goods
A74: ACH-EN-EL-0002 | B74: 1.22e+18 | C74: 160050 - Liquid Plate Sealer | D74: EN | E74: EL | F74: 160050 - Liquid Plate Sealer | H74: Candoor | I74: ul | J74: INR 0.25 | K74: 0 | M74: 2-8 Fridge R_D Section | N74: BioAzure Technologies Pvt. Ltd. | O74: Active | P74: goods
A75: ACH-EN-EL-0003 | B75: 1.22e+18 | C75: 160050 - Liquid Plate Sealer | D75: EN | E75: EL | F75: 160050 - Liquid Plate Sealer | H75: Candoor | I75: ul | J75: INR 0.25 | K75: 0 | M75: Room Temperature R_D Section | N75: BioAzure Technologies Pvt. Ltd. | O75: Active | P75: goods
A76: ACH-RD-CH-0039 | B76: 1.22e+18 | C76: MB098-Lysozyme | D76: RD | E76: CH | F76: MB098-Lysozyme | H76: Himedia | I76: mg | J76: INR 5.23 | K76: 0 | M76: 2-8 Fridge R_D Section | O76: Active | P76: goods
A77: ACH-RD-CH-0040 | B77: 1.22e+18 | C77: MB098-Lysozyme | D77: RD | E77: CH | F77: MB098-Lysozyme | H77: Himedia | I77: mg | J77: INR 5.23 | K77: 0 | M77: -20 Fridge R_D Section | O77: Active | P77: goods
A78: ACH-RD-CH-0041 | B78: 1.22e+18 | C78: 900889-Lithium Phenyl -2, 4,6 - Trimethylbenzene - Yl phosphonate | D78: RD | E78: CH | F78: 900889-Lithium Phenyl -2, 4,6 - Trimethylbenzene - Yl phosphonate | H78: Sigma | I78: mg | J78: INR 17.11 | K78: 700 | M78: 2-8 Fridge R_D Section | N78: Sigma Aldrich Chemicals Pvt Ltd | O78: Active | P78: goods
A79: ACH-RD-AB-0010 | B79: 1.22e+18 | C79: 100019 - Anti-H LH 5303 SPRN-1 | D79: RD | E79: AB | F79: 100019 - Anti-H LH 5303 SPRN-1 | H79: Medix | I79: ug | J79: INR 2.25 | K79: 0 | M79: 2-8 Fridge R_D Section | N79: Medix | O79: Active | P79: goods
A80: ACH-RD-KT-0004 | B80: 1.22e+18 | C80: Lepto IGM Microlisa | D80: RD | E80: KT | F80: Lepto IGM Microlisa | H80: J Mitra | I80: Test | J80: INR 119.79 | K80: 0 | M80: 2-8 Fridge R_D Section | N80: Aspire Diagnoline Pvt. Ltd | O80: Active | P80: goods
A81: ACH-RD-CH-0042 | B81: 1.22e+18 | C81: L9017- Lectin from Fahseolusvulgaris | D81: RD | E81: CH | F81: L9017- Lectin from Fahseolusvulgaris | H81: Sigma | I81: ug | J81: INR 7.71 | K81: 0 | M81: 2-8 Fridge R_D Section | O81: Active | P81: goods
A82: ACH-RD-AB-0011 | B82: 1.22e+18 | C82: HCGCD- Monoclonal Antibodt HCG | D82: RD | E82: AB | F82: HCGCD- Monoclonal Antibodt HCG | H82: Fapon Biotech | I82: ul | J82: INR 0.346 | K82: 0 | M82: 2-8 Fridge R_D Section | O82: Active | P82: goods
A83: ACH-RD-CH-0043 | B83: 1.22e+18 | C83: MIDARDI Cartridge | D83: RD | E83: CH | F83: MIDARDI Cartridge | H83: BiFlow | I83: No | J83: INR 1.00 | K83: 0 | M83: 2-8 Fridge R_D Section | N83: BiFlow | O83: Active | P83: goods
A84: ACH-RD-CH-0044 | B84: 1.22e+18 | C84: C1063 - Chorionic gonadotropin Human | D84: RD | E84: CH | F84: C1063 - Chorionic gonadotropin Human | H84: Sigma | I84: ul | J84: INR 6.74 | K84: 0 | M84: 2-8 Fridge R_D Section | N84: Sigma Aldrich Chemicals Pvt Ltd | O84: Active | P84: goods
A85: ACH-RD-CH-0045 | B85: 1.22e+18 | C85: M6500-Cysteamine Hydrochloride | D85: RD | E85: CH | F85: M6500-Cysteamine Hydrochloride | H85: Sigma | I85: mg | J85: INR 0.126 | K85: 0 | M85: 2-8 Fridge R_D Section | N85: Sigma Aldrich Chemicals Pvt Ltd | O85: Active | P85: goods
A86: ACH-RD-CH-0046 | B86: 1.22e+18 | C86: 2-Bromo 17B-Estradial | D86: RD | E86: CH | F86: 2-Bromo 17B-Estradial | H86: TRC | I86: ug | J86: INR 0.11 | K86: 0 | M86: 2-8 Fridge R_D Section | N86: Toronto Research Chemicals, Inc. | O86: Active | P86: goods
A87: ACH-RD-FL-0020 | B87: 1.22e+18 | C87: Fluidmag-CT | D87: RD | E87: FL | F87: Fluidmag-CT | H87: Chemicell | I87: ug | J87: INR 0.32 | K87: 0 | M87: 2-8 Fridge R_D Section | O87: Active | P87: goods
A88: ACH-RD-CH-0047 | B88: 1.22e+18 | C88: P8375 - Peroxidase from horseradish | D88: RD | E88: CH | F88: P8375 - Peroxidase from horseradish | H88: Sigma | I88: No | J88: INR 67.15 | K88: 0 | M88: 2-8 Fridge R_D Section | N88: Sigma Aldrich Chemicals Pvt Ltd | O88: Active | P88: goods
A89: ACH-RD-CH-0048 | B89: 1.22e+18 | C89: 77332- Peroxidase from horseradish | D89: RD | E89: CH | F89: 77332- Peroxidase from horseradish | H89: Fluka | I89: ug | J89: INR 0.10 | K89: 0 | M89: 2-8 Fridge R_D Section | O89: Active | P89: goods
A90: ACH-RD-AB-0012 | B90: 1.22e+18 | C90: P0012-02 - Rabitt Anti Goat IGG Absorbed | D90: RD | E90: AB | F90: P0012-02 - Rabitt Anti Goat IGG Absorbed | H90: Abexome | I90: ug | J90: INR 0.10 | K90: 0 | M90: 2-8 Fridge R_D Section | O90: Active | P90: goods
A91: ACH-RD-AB-0013 | B91: 1.22e+18 | C91: 100038 - Anti-H PRL 5601 - SP-1 | D91: RD | E91: AB | F91: Assay Development | H91: Medix | I91: ug | J91: INR 3.58 | K91: 0 | M91: 2-8 Fridge R_D Section | N91: Medix | O91: Active | P91: goods
A92: ACH-RD-CH-0049 | B92: 1.22e+18 | C92: P3277 - Progesterone | D92: RD | E92: CH | F92: P3277 - Progesterone | H92: Sigma | I92: ug | J92: INR 0.268 | K92: 0 | M92: 2-8 Fridge R_D Section | N92: Sigma Aldrich Chemicals Pvt Ltd | O92: Active | P92: goods
A93: ACH-RD-AB-0014 | B93: 1.22e+18 | C93: NO1275H - Hama Serum | D93: RD | E93: AB | F93: NO1275H - Hama Serum | H93: Meridian | I93: ul | J93: INR 7.125 | K93: 0 | M93: 2-8 Fridge R_D Section | N93: Meridian Life Science Inc | O93: Active | P93: goods
A94: ACH-RD-AB-0015 | B94: 1.22e+18 | C94: A01270H - Rheumatoid Factor CTRL Plasma | D94: RD | E94: AB | F94: A01270H - Rheumatoid Factor CTRL Plasma | H94: Meridian | I94: ul | J94: INR 15.15 | K94: 0 | M94: 2-8 Fridge R_D Section | N94: Meridian Life Science Inc | O94: Active | P94: goods
A95: ACH-RD-CH-0050 | B95: 1.22e+18 | C95: 122-49 - Carbon Coinductive Link | D95: RD | E95: CH | F95: 122-49 - Carbon Coinductive Link | H95: Creative Materials | I95: mg | J95: INR 0.052 | K95: 0 | M95: 2-8 Fridge R_D Section | O95: Active | P95: goods
A96: ACH-RD-CH-0051 | B96: 1.22e+18 | C96: 113-12 - Thinner Solvent | D96: RD | E96: CH | F96: 113-12 - Thinner Solvent | H96: Creative Materials | I96: ug | J96: INR 0.0286 | K96: 0 | M96: 2-8 Fridge R_D Section | O96: Active | P96: goods
A97: ACH-RD-KT-0005 | B97: 1.22e+18 | C97: Ni-NTA Agarose | D97: RD | E97: KT | F97: Ni-NTA Agarose | H97: Qiagen | I97: ul | J97: INR 1.10 | K97: 0 | M97: 2-8 Fridge R_D Section | O97: Active | P97: goods
A98: ACH-RD-CH-0052 | B98: 1.22e+18 | C98: 655201 -Poly (3,4-ethylendioxythiophene) - Poly (styrene sulfonate) Formulations for high conductivity coatings | D98: RD | E98: CH | F98: 655201 -Poly (3,4-ethylendioxythiophene) - Poly (styrene sulfonate) Formulations for high conductivity coatings | H98: Sigma | I98: mg | J98: INR 0.50 | K98: 0 | M98: 2-8 Fridge R_D Section | N98: Sigma Aldrich Chemicals Pvt Ltd | O98: Active | P98: goods
A99: ACH-RD-CH-0053 | B99: 1.22e+18 | C99: 455008 - Poly (ethylene glycol) diacrylate | D99: RD | E99: CH | F99: Assay Development | H99: Sigma | I99: ul | J99: INR 0.039 | K99: 1081600 | M99: 2-8 Fridge R_D Section | N99: Sigma Aldrich Chemicals Pvt Ltd | O99: Active | P99: goods
A100: ACH-RD-CH-0054 | B100: 1.22e+18 | C100: 455008 - Poly (ethylene glycol) diacrylate | D100: RD | E100: CH | F100: Assay Development | H100: Sigma | I100: ul | J100: INR 0.039 | K100: 1081600 | M100: Room Temperature R_D Section | N100: Sigma Aldrich Chemicals Pvt Ltd | O100: Active | P100: goods
A101: ACH-RD-CH-0055 | B101: 1.22e+18 | C101: 447943 - Poly (ethylene glycol) methyl ethier methacrylate | D101: RD | E101: CH | F101: 447943 - Poly (ethylene glycol) methyl ethier methacrylate | H101: Sigma | I101: ul | J101: INR 0.046 | K101: 0 | M101: 2-8 Fridge R_D Section | O101: Active | P101: goods
...

Sheet Employees
A1: Employee Name
A2: Dhananjaya Dendukuri
A3: HARSHINI J A
A4: DIVYA PRIYA A
A5: KAVI VARSHINI M
A6: Deepika N
A7: SAGAR Chichalappa DEVAKATE
A8: Neha M Manashetty
A9: Raghavendra Annacharya Katti
A10: Riddhiman Ganguly
A11: Soumya Bhattacharya
A12: Inchara Venugopal
... A55: Krishna Jitendra Vekariya

Sheet 7. ARN Pending
A1: ID | B1: Timestamp | C1: Material | D1: Brand | E1: Qty | F1: GRN No. | G1: Dept | H1: Subcat | I1: Requested By | J1: Notes | K1: Status | L1: Corrected Dept | M1: Corrected Subcat | N1: Rejection Reason | O1: Unit | P1: Final ARN | Q1: GRN Status | R1: Vendor | S1: PO No. | T1: Duplicate Acknowledged | U1: Amount Paid | V1: Bill / Invoice No. | W1: Paid By | X1: Reimbursement Status | Y1: Procurement Request No. | Z1: Requester Dept | AA1: Location
A2: 601c7cb3-c060-4d83-b6ba-77ac3f21eb4f | B2: 46212.982 | C2: N4074-Universal Corrugated Box- 5 Ply- Custom Board- 60x40x30 cm-OD Plain Brown- PCID-12280 | E2: 1 | F2: GR/DD/1040_2 | G2: MF | H2: PM | I2: Saurabh Yadav | K2: Approved
A3: 5f4e1f9e-17a5-49eb-8e08-b76c9384e02d | B3: 46212.983 | C3: N4074-Universal Corrugated Box- 5 Ply | E3: 1 | F3: GR/DD/1040 | G3: MF | H3: PM | I3: JAYASHREE G | K3: Approved
A4: 3310a2fe-d165-4d25-ba3c-670ba120aeeb | B4: 46212.991 | C4: D(+)-TREHALOSE DIHYDRATE, FOR MICRO | E4: 1 | F4: GR/DD/1038 | G4: RD | H4: CH | I4: KOMAL NAVIN BHANUSHALI | K4: Approved
A5: d48c6ec7-7070-4be8-92d2-a63c876e1087 | B5: 46213.203 | C5: Cap with EPDOM O Ring Sterile | E5: 10 | F5: GR/DD/1035 | G5: RD | H5: CM | I5: KOMAL NAVIN BHANUSHALI | K5: Approved | O5: No
A6: f6bcc771-3f82-4b0e-b2ef-e933788b8562 | B6: 46216.146 | C6: STICKER-ACHIRA-RPT-COLETN-BFR-BOX STKR-PAPER | D6: Elegant Labels | E6: 12 | F6: GR/DD/1043_4 | G6: MF | H6: PM | I6: Sudarshan Hegde | K6: Approved | O6: No | P6: ACH-MF-PM-0032 | Q6: Confirmed | R6: Elegant Labels | S6: ACHIRA/26-27/53 | Y6: MFG-358 | Z6: MF
A7: 6acf1bdf-95d6-41fb-bc92-f29131a3c953 | B7: 46216.187 | C7: STICKER-ACHIRA-RPT-ASSY-POUCH STKR-PAPER | E7: 12 | F7: GR/DD/1043_3 | G7: MF | H7: PM | I7: Sudarshan Hegde | K7: Approved | O7: No | P7: ACH-MF-PM-0033 | Q7: Confirmed | R7: Elegant Labels | S7: ACHIRA/26-27/53 | Y7: MFG-356 | Z7: MF
A8: a284c46e-5e12-45a6-8085-2d2899eb3e4a | B8: 46216.383 | C8: STICKER-ACHIRA-RPT-ASSY BFR BTL-TP STKR | D8: Elegant label | E8: 12 | F8: GR/DD/1043_2 | G8: MF | H8: LB | I8: Sudarshan Hegde | K8: Approved | O8: No | P8: ACH-MF-LB-0013 | Q8: Confirmed | R8: Elegant Labels | S8: ACHIRA/26-27/53 | Y8: MFG-385 | Z8: MF
A9: a9d98bc5-ac0f-4317-880d-41c698f0987b | B9: 46216.408 | C9: Micro Cover Glass Square No:1 22x22mm (pkt of 10 GMS) | D9: VASA scientific | E9: 20 | F9: GR/DD/1042 | G9: MF | H9: RM | I9: Sudarshan Hegde | K9: Approved | O9: No | P9: ACH-MF-RM-0008 | Q9: Confirmed | R9: Vasa Sciebtific Co., | S9: ACHIRA/26-27/54 | Y9: MFG-384 | Z9: MF

Sheet 6. Material Requests
A1: Request ID | B1: Date | C1: Time | D1: ARN | E1: Item Name | F1: Dept | G1: Unit | H1: Warehouse | I1: Qty Requested | J1: Purpose | K1: Priority | L1: Required By | M1: Requester Name | N1: Requester Dept | O1: Status | P1: Issued On | Q1: Adj ID | R1: Notes | S1: Timestamp
A2: MR-0003 | B2: 46272 | C2: 0.74791667 | D2: ACH-GN-IT-0003 | E2: Raspberry Pi 4 8GB RAM i All new Raspberry Pi Desktop Computer | F2: GN | G2: pcs | I2: 1 | J2: sdssd | K2: Normal | M2: Eslavath Mahesh | N2: Quality & Regulatory | O2: Pending | S2: 2026-07-09T12:27:59.858Z
A3: MR-0005 | B3: 14/07/2026 | C3: 0.33888889 | D3: ACH-MF-RM-0008 | E3: Micro Cover Glass Square No:1 22x22mm (pkt of 10 GMS) | F3: MF | G3: No | I3: 1 | J3: for testing | K3: Normal | M3: Saurabh Yadav | N3: Manufacturing | O3: Pending | S3: 2026-07-14T02:38:53.548Z

Sheet 3. Live Stock Summary
A1: ACHIRA LABS — LIVE STOCK SUMMARY (Auto-Calculated · Do Not Edit)
A2: 🔄 All values here are calculated from '2. Adjustment Log'. Current Stock = Opening Stock (Zoho) + Total Inward − Total Deducted. Stock Status: 🟢 OK | 🟡 Low (≤ Reorder Level) | 🔴 Critical (≤ 50% of Reorder)
A3: ARN | B3: Item Name | C3: Dept | D3: Unit | E3: Opening Stock (Zoho) | F3: Total Inward | G3: Total Deducted | H3: Current Stock | I3: Reorder Level | J3: Stock Status | K3: Last Adj Date | L3: Warehouse | M3: Notes
A4: ACH-RD-AB-0002 | B4: =IFERROR(VLOOKUP(A4,'1. Master Item List'!A:C,3,0),"") -> 375.1% -Carboxylate -1.5 Mmol/g | C4: =IFERROR(VLOOKUP(A4,'1. Master Item List'!A:D,4,0),"") -> RD | D4: =IFERROR(VLOOKUP(A4,'1. Master Item List'!A:I,9,0),"") -> ul | E4: 14350 | F4: =SUMPRODUCT((('2. Adjustment Log'!D$4:D$1997=A4)*('2. Adjustment Log'!K$4:K$1997="+Add")*IF(ISNUMBER('2. Adjustment Log'!J$4:J$1997),'2. Adjustment Log'!J$4:J$1997,0))) -> #NAME? | G4: =SUMPRODUCT((('2. Adjustment Log'!D$4:D$1997=A4)*('2. Adjustment Log'!K$4:K$1997="-Deduct")*IF(ISNUMBER('2. Adjustment Log'!J$4:J$1997),'2. Adjustment Log'!J$4:J$1997,0))) -> #NAME? | H4: =E4+F4-G4 -> #NAME? | I4: =IFERROR(VLOOKUP(A4,'1. Master Item List'!A:L,12,0)+0,0) -> 0 | J4: =IF(I4=0,"🟢 OK",IF(H4<=I4*0.5,"🔴 Critical",IF(H4<=I4,"🟡 Low","🟢 OK"))) -> 🟢 OK | K4: =IFERROR(maxifs('2. Adjustment Log'!B$4:B$1997,'2. Adjustment Log'!D$4:D$1997,A4),"No entries") -> 46241 | L4: =IFERROR(VLOOKUP(A4,'1. Master Item List'!A:M,13,0),"") -> 2-8 Fridge R_D Section
A5: ACH-RD-KT-0001 | B5: =IFERROR(VLOOKUP(A5,'1. Master Item List'!A:C,3,0),"") -> Chikungunya IGM ELISA - MicroLisa | C5: =IFERROR(VLOOKUP(A5,'1. Master Item List'!A:D,4,0),"") -> RD | D5: =IFERROR(VLOOKUP(A5,'1. Master Item List'!A:I,9,0),"") -> Test | E5: 0 | F5: =SUMPRODUCT((('2. Adjustment Log'!D$4:D$1997=A5)*('2. Adjustment Log'!K$4:K$1997="+Add")*IF(ISNUMBER('2. Adjustment Log'!J$4:J$1997),'2. Adjustment Log'!J$4:J$1997,0))) -> #NAME? | G5: =SUMPRODUCT((('2. Adjustment Log'!D$4:D$1997=A5)*('2. Adjustment Log'!K$4:K$1997="-Deduct")*IF(ISNUMBER('2. Adjustment Log'!J$4:J$1997),'2. Adjustment Log'!J$4:J$1997,0))) -> #NAME? | H5: =E5+F5-G5 -> #NAME? | I5: =IFERROR(VLOOKUP(A5,'1. Master Item List'!A:L,12,0)+0,0) -> 0 | J5: =IF(I5=0,"🟢 OK",IF(H5<=I5*0.5,"🔴 Critical",IF(H5<=I5,"🟡 Low","🟢 OK"))) -> 🟢 OK | K5: =IFERROR(maxifs('2. Adjustment Log'!B$4:B$1997,'2. Adjustment Log'!D$4:D$1997,A5),"No entries") -> 46241 | L5: =IFERROR(VLOOKUP(A5,'1. Master Item List'!A:M,13,0),"") -> 2-8 Fridge R_D Section
A6: ACH-EN-EQ-0001 | B6: =IFERROR(VLOOKUP(A6,'1. Master Item List'!A:C,3,0),"") -> CORSAIR DDR5 5200 MHZ 16GB DDR5 | C6: =IFERROR(VLOOKUP(A6,'1. Master Item List'!A:D,4,0),"") -> EN | D6: =IFERROR(VLOOKUP(A6,'1. Master Item List'!A:I,9,0),"") -> pcs | E6: 0 | F6: =SUMPRODUCT((('2. Adjustment Log'!D$4:D$1997=A6)*('2. Adjustment Log'!K$4:K$1997="+Add")*IF(ISNUMBER('2. Adjustment Log'!J$4:J$1997),'2. Adjustment Log'!J$4:J$1997,0))) -> #NAME? | G6: =SUMPRODUCT((('2. Adjustment Log'!D$4:D$1997=A6)*('2. Adjustment Log'!K$4:K$1997="-Deduct")*IF(ISNUMBER('2. Adjustment Log'!J$4:J$1997),'2. Adjustment Log'!J$4:J$1997,0))) -> #NAME? | H6: =E6+F6-G6 -> #NAME? | I6: =IFERROR(VLOOKUP(A6,'1. Master Item List'!A:L,12,0)+0,0) -> 0 | J6: =IF(I6=0,"🟢 OK",IF(H6<=I6*0.5,"🔴 Critical",IF(H6<=I6,"🟡 Low","🟢 OK"))) -> 🟢 OK | K6: =IFERROR(maxifs('2. Adjustment Log'!B$4:B$1997,'2. Adjustment Log'!D$4:D$1997,A6),"No entries") -> 0 | L6: =IFERROR(VLOOKUP(A6,'1. Master Item List'!A:M,13,0),"")
A7: ACH-RD-CH-0001 | B7: =IFERROR(VLOOKUP(A7,'1. Master Item List'!A:C,3,0),"") -> A1653-ALBUMIN FROM HUMAN SERUM | C7: =IFERROR(VLOOKUP(A7,'1. Master Item List'!A:D,4,0),"") -> RD | D7: =IFERROR(VLOOKUP(A7,'1. Master Item List'!A:I,9,0),"") -> ug | E7: 0 | F7: =SUMPRODUCT((('2. Adjustment Log'!D$4:D$1997=A7)*('2. Adjustment Log'!K$4:K$1997="+Add")*IF(ISNUMBER('2. Adjustment Log'!J$4:J$1997),'2. Adjustment Log'!J$4:J$1997,0))) -> #NAME? | G7: =SUMPRODUCT((('2. Adjustment Log'!D$4:D$1997=A7)*('2. Adjustment Log'!K$4:K$1997="-Deduct")*IF(ISNUMBER('2. Adjustment Log'!J$4:J$1997),'2. Adjustment Log'!J$4:J$1997,0))) -> #NAME? | H7: =E7+F7-G7 -> #NAME? | I7: =IFERROR(VLOOKUP(A7,'1. Master Item List'!A:L,12,0)+0,0) -> 0 | J7: =IF(I7=0,"🟢 OK",IF(H7<=I7*0.5,"🔴 Critical",IF(H7<=I7,"🟡 Low","🟢 OK"))) -> 🟢 OK | K7: =IFERROR(maxifs('2. Adjustment Log'!B$4:B$1997,'2. Adjustment Log'!D$4:D$1997,A7),"No entries") -> 46272 | L7: =IFERROR(VLOOKUP(A7,'1. Master Item List'!A:M,13,0),"") -> 2-8 Fridge R_D Section
A8: ACH-RD-CH-0002 | B8: =IFERROR(VLOOKUP(A8,'1. Master Item List'!A:C,3,0),"") -> 2FSH2 F2 Anti FSH Beta Chain | C8: =IFERROR(VLOOKUP(A8,'1. Master Item List'!A:D,4,0),"") -> RD | D8: =IFERROR(VLOOKUP(A8,'1. Master Item List'!A:I,9,0),"") -> ug | E8: 50000 | F8: =SUMPRODUCT((('2. Adjustment Log'!D$4:D$1997=A8)*('2. Adjustment Log'!K$4:K$1997="+Add")*IF(ISNUMBER('2. Adjustment Log'!J$4:J$1997),'2. Adjustment Log'!J$4:J$1997,0))) -> #NAME? | G8: =SUMPRODUCT((('2. Adjustment Log'!D$4:D$1997=A8)*('2. Adjustment Log'!K$4:K$1997="-Deduct")*IF(ISNUMBER('2. Adjustment Log'!J$4:J$1997),'2. Adjustment Log'!J$4:J$1997,0))) -> #NAME? | H8: =E8+F8-G8 -> #NAME? | I8: =IFERROR(VLOOKUP(A8,'1. Master Item List'!A:L,12,0)+0,0) -> 0 | J8: =IF(I8=0,"🟢 OK",IF(H8<=I8*0.5,"🔴 Critical",IF(H8<=I8,"🟡 Low","🟢 OK"))) -> 🟢 OK | K8: =IFERROR(maxifs('2. Adjustment Log'!B$4:B$1997,'2. Adjustment Log'!D$4:D$1997,A8),"No entries") -> 46302 | L8: =IFERROR(VLOOKUP(A8,'1. Master Item List'!A:M,13,0),"") -> 2-8 Fridge R_D Section
A9: ACH-RD-CH-0003 | B9: =IFERROR(VLOOKUP(A9,'1. Master Item List'!A:C,3,0),"") -> SM01-0050-Assay Diluent - Protein Free | C9: =IFERROR(VLOOKUP(A9,'1. Master Item List'!A:D,4,0),"") -> RD | D9: =IFERROR(VLOOKUP(A9,'1. Master Item List'!A:I,9,0),"") | E9: 5000 | F9: =SUMPRODUCT((('2. Adjustment Log'!D$4:D$1997=A9)*('2. Adjustment Log'!K$4:K$1997="+Add")*IF(ISNUMBER('2. Adjustment Log'!J$4:J$1997),'2. Adjustment Log'!J$4:J$1997,0))) -> #NAME? | G9: =SUMPRODUCT((('2. Adjustment Log'!D$4:D$1997=A9)*('2. Adjustment Log'!K$4:K$1997="-Deduct")*IF(ISNUMBER('2. Adjustment Log'!J$4:J$1997),'2. Adjustment Log'!J$4:J$1997,0))) -> #NAME? | H9: =E9+F9-G9 -> #NAME? | I9: =IFERROR(VLOOKUP(A9,'1. Master Item List'!A:L,12,0)+0,0) -> 0 | J9: =IF(I9=0,"🟢 OK",IF(H9<=I9*0.5,"🔴 Critical",IF(H9<=I9,"🟡 Low","🟢 OK"))) -> 🟢 OK | K9: =IFERROR(maxifs('2. Adjustment Log'!B$4:B$1997,'2. Adjustment Log'!D$4:D$1997,A9),"No entries") -> 0 | L9: =IFERROR(VLOOKUP(A9,'1. Master Item List'!A:M,13,0),"") -> 2-8 Fridge R_D Section
A10: ACH-RD-CH-0004 | B10: =IFERROR(VLOOKUP(A10,'1. Master Item List'!A:C,3,0),"") -> A3699-Acrylamide/bis-Acrylamide | C10: =IFERROR(VLOOKUP(A10,'1. Master Item List'!A:D,4,0),"") -> RD | D10: =IFERROR(VLOOKUP(A10,'1. Master Item List'!A:I,9,0),"") -> ul | E10: 0 | F10: =SUMPRODUCT((('2. Adjustment Log'!D$4:D$1997=A10)*('2. Adjustment Log'!K$4:K$1997="+Add")*IF(ISNUMBER('2. Adjustment Log'!J$4:J$1997),'2. Adjustment Log'!J$4:J$1997,0))) -> #NAME? | G10: =SUMPRODUCT((('2. Adjustment Log'!D$4:D$1997=A10)*('2. Adjustment Log'!K$4:K$1997="-Deduct")*IF(ISNUMBER('2. Adjustment Log'!J$4:J$1997),'2. Adjustment Log'!J$4:J$1997,0))) -> #NAME? | H10: =E10+F10-G10 -> #NAME? | I10: =IFERROR(VLOOKUP(A10,'1. Master Item List'!A:L,12,0)+0,0) -> 0 | J10: =IF(I10=0,"🟢 OK",IF(H10<=I10*0.5,"🔴 Critical",IF(H10<=I10,"🟡 Low","🟢 OK"))) -> 🟢 OK | K10: =IFERROR(maxifs('2. Adjustment Log'!B$4:B$1997,'2. Adjustment Log'!D$4:D$1997,A10),"No entries") -> 0 | L10: =IFERROR(VLOOKUP(A10,'1. Master Item List'!A:M,13,0),"") -> 2-8 Fridge R_D Section
A11: ACH-RD-AB-0003 | B11: =IFERROR(VLOOKUP(A11,'1. Master Item List'!A:C,3,0),"") -> 100022-Anti-H LH-5304-SP-5 | C11: =IFERROR(VLOOKUP(A11,'1. Master Item List'!A:D,4,0),"") -> RD | D11: =IFERROR(VLOOKUP(A11,'1. Master Item List'!A:I,9,0),"") -> ug | E11: 2600 | F11: =SUMPRODUCT((('2. Adjustment Log'!D$4:D$1997=A11)*('2. Adjustment Log'!K$4:K$1997="+Add")*IF(ISNUMBER('2. Adjustment Log'!J$4:J$1997),'2. Adjustment Log'!J$4:J$1997,0))) -> #NAME? | G11: =SUMPRODUCT((('2. Adjustment Log'!D$4:D$1997=A11)*('2. Adjustment Log'!K$4:K$1997="-Deduct")*IF(ISNUMBER('2. Adjustment Log'!J$4:J$1997),'2. Adjustment Log'!J$4:J$1997,0))) -> #NAME? | H11: =E11+F11-G11 -> #NAME? | I11: =IFERROR(VLOOKUP(A11,'1. Master Item List'!A:L,12,0)+0,0) -> 0 | J11: =IF(I11=0,"🟢 OK",IF(H11<=I11*0.5,"🔴 Critical",IF(H11<=I11,"🟡 Low","🟢 OK"))) -> 🟢 OK | K11: =IFERROR(maxifs('2. Adjustment Log'!B$4:B$1997,'2. Adjustment Log'!D$4:D$1997,A11),"No entries") -> 0 | L11: =IFERROR(VLOOKUP(A11,'1. Master Item List'!A:M,13,0),"") -> 2-8 Fridge R_D Section
A13: 💡 To add more items to this summary: copy any formula row above and paste below, then update the ARN in column A.

Sheet 2. Adjustment Log
A1: ACHIRA LABS — INVENTORY ADJUSTMENT LOG
A2: 📋 HOW TO USE: (1) Enter Adj ID manually or use formula. (2) Select ARN from dropdown — Item Name & Unit auto-fill. (3) Select Adjustment Type and enter Quantity. (4) Fill Reason and your name. (5) Leave Tally Sync Status as 'Not Synced'.
A3: Adj ID | B3: Date | C3: Time | D3: ARN | E3: Item Name (auto-fill) | F3: Dept | G3: Unit (auto-fill) | H3: Warehouse | I3: Adj Type | J3: Quantity | K3: Effect | L3: GRN No. | M3: Reason / Notes | N3: Issued To | O3: Project | P3: Stores Manager | Q3: Status | R3: Approved By | S3: Tally Sync | T3: Remarks
A4: ADJ-0001 | B4: 2026-07-08 | C4: 09:30 | D4: ACH-RD-CH-0001 | E4: =IFERROR(VLOOKUP(D4,'1. Master Item List'!A:C,3,0),"") -> A1653-ALBUMIN FROM HUMAN SERUM | F4: =IFERROR(VLOOKUP(D4,'1. Master Item List'!A:D,4,0),"") -> RD | G4: =IFERROR(VLOOKUP(D4,'1. Master Item List'!A:I,9,0),"") -> ug | H4: 2-8 Fridge R_D Section | I4: Inward | J4: 1000 | K4: +Add | L4: BATCH-001 | M4: Stock received from vendor | P4: Store Manager | Q4: Approved | R4: Lab Head | S4: Not Synced
A5: ADJ-0002 | B5: 2026-07-08 | C5: 10:15 | D5: ACH-MF-CT-0005 | E5: =IFERROR(VLOOKUP(D5,'1. Master Item List'!A:C,3,0),"") -> Valve Retainer | F5: =IFERROR(VLOOKUP(D5,'1. Master Item List'!A:D,4,0),"") -> MF | G5: =IFERROR(VLOOKUP(D5,'1. Master Item List'!A:I,9,0),"") -> pcs | H5: MFG Store | I5: Damage | J5: 50 | K5: -Deduct | M5: Damaged during assembly | P5: Store Manager | Q5: Pending | S5: Not Synced | T5: Awaiting approval
A6: ADJ-0003
A7: ADJ-0013 | B7: 46241 | C7: 0.74027778 | D7: ACH-RD-KT-0001 | E7: SM01-0050-Assay Diluent - Protein Free | F7: RD | H7: 2-8 Fridge R_D Section | I7: Issue | J7: 1 | K7: -Deduct | M7: Testing | P7: Siddharth R | Q7: Testing | R7: Store Manager 1 | S7: Pending | U7: Not Synced | V7: 2026-07-08T12:16:40.138Z
A8: ADJ-0019 | B8: 46241 | C8: 0.84027778 | D8: ACH-RD-CH-0002 | E8: SM01-0050-Assay Diluent - Protein Free | F8: RD | H8: 2-8 Fridge R_D Section | I8: Issue | J8: 1 | K8: -Deduct | M8: TEST | P8: Sid | Q8: TEst | R8: Shiva Raj | S8: Pending | U8: Not Synced | V8: 2026-07-08T14:40:03.829Z
A9: ADJ-0021 | B9: 46241 | C9: 0.98472222 | D9: ACH-RD-AB-0002 | E9: 131050- Antibody Stabilizer | F9: RD | G9: ul | H9: 2-8 Fridge R_D Section | I9: Issue | J9: 1 | K9: -Deduct | M9: Testing done | N9: Siddharth R | O9: TFT (Software test) | P9: Shiva Raj | Q9: Pending | S9: Not Synced | T9: 2026-07-08T18:08:28.281Z
A10: ADJ-0023 | B10: 46272 | C10: 0.43194444 | D10: ACH-EN-EL-0005 | E10: Feather nRF52 Bluefruit LE nRF52832 ARM Cortex M4F | F10: EN | G10: pcs | H10: Engineering Store | I10: Issue | J10: 1 | K10: -Deduct | M10: testing | N10: Siddharth R | O10: Testing | P10: Shiva Raj | Q10: Pending | S10: Not Synced | T10: 2026-07-09T04:52:13.815Z
A11: ADJ-0040 | B11: 46272 | C11: 0.53194444 | D11: ACH-RD-CH-0008 | E11: A3059-Albumin from Bovine Serum | F11: RD | G11: mg | H11: 2-8 Fridge R_D Section | I11: Issue | J11: 1 | K11: -Deduct | M11: dfgh | N11: ghfds | O11: dfghjk | P11: Raghavendra Katti | Q11: Pending | S11: Not Synced | T11: 2026-07-09T07:16:26.470Z
A12: CONFIRM-001 | B12: 46272 | C12: 0.53125 | D12: ACH-RD-CH-0001 | E12: Test Item | F12: RD | G12: mg | H12: 2-8 Fridge R_D Section | I12: Inward | J12: 5 | K12: #NAME? | L12: GR/DD/001 | M12: Confirmation test | P12: Siddharth R | Q12: Pending | S12: Not Synced | T12: 2026-07-09T07:17:39.078Z
A13: ADJ-0042 | B13: 46302 | C13: 0.45902778 | D13: ACH-RD-CH-0002 | E13: 2FSH2 F2 Anti FSH Beta Chain | F13: RD | G13: ug | H13: 2-8 Fridge R_D Section | I13: Issue | J13: 1 | K13: -Deduct | M13: Dummy entry | N13: Siddharth R | O13: Dummy entry | P13: Shiva Raj | Q13: Pending | S13: Not Synced | T13: 2026-07-10T05:31:09.671Z
A14: ADJ-0044 | B14: 13/07/2026 | C14: 0.50277778 | D14: ACH-EN-ME-0304 | E14: FIAI-OH-G-001 - Filter retainer | F14: EN | G14: pcs | H14: Engineering Store | I14: Inward | J14: 80 | K14: #NAME? | M14: New parts arrived | P14: Siddharth R | Q14: Pending | S14: Not Synced | T14: 2026-07-13T06:34:08.645Z
A15: ADJ-0045 | B15: 13/07/2026 | C15: 0.51875 | D15: ACH-EN-ME-0304 | E15: FIAI-OH-G-001 - Filter retainer | F15: EN | G15: pcs | H15: Engineering Store | I15: Inward | J15: 80 | K15: +Add | M15: Restock | P15: Shiva Raj | Q15: Pending | S15: Not Synced | T15: 2026-07-13T06:57:39.655Z
A16: ADJ-0048 | B16: 13/07/2026 | C16: 0.65416667 | D16: ACH-EN-ME-0304 | E16: FIAI-OH-G-001 - Filter retainer | F16: EN | G16: pcs | H16: Engineering Store | I16: Inward | J16: 80 | K16: +Add | M16: New stock | N16: Nitin CM | P16: Siddharth R | Q16: Pending | S16: Not Synced | T16: 2026-07-13T10:12:08.691Z
A17: ADJ-0049 | B17: 46216 | C17: 0.90427083 | D17: ACH-MF-LB-0013 | E17: STICKER-ACHIRA-RPT-ASSY BFR BTL-TP STKR | F17: MF | G17: No | I17: Inward | J17: 12 | K17: +Add | L17: GR/DD/1043_2 | M17: Opening stock — new item approved via ARN Assignment | P17: Sudarshan Hegde | Q17: Approved | R17: Sudarshan Hegde | S17: Not Synced | T17: 2026-07-13T16:12:09.679Z
A18: ADJ-0050 | B18: 46216 | C18: 0.90711806 | D18: ACH-MF-RM-0008 | E18: Micro Cover Glass Square No:1 22x22mm (pkt of 10 GMS) | F18: MF | G18: No | I18: Inward | J18: 20 | K18: +Add | L18: GR/DD/1042 | M18: Opening stock — new item approved via ARN Assignment | P18: Sudarshan Hegde | Q18: Approved | R18: Sudarshan Hegde | S18: Not Synced | T18: 2026-07-13T16:16:15.432Z
A19: ADJ-0051 | B19: 46216 | C19: 0.9290162 | D19: ACH-MF-RM-0008 | E19: Micro Cover Glass Square No:1 22x22mm (pkt of 10 GMS) | F19: MF | G19: No | I19: Inward | J19: 20 | K19: +Add | L19: GR/DD/1042 | M19: Opening stock — new item approved via ARN Assignment | P19: Sudarshan Hegde | Q19: Approved | R19: Sudarshan Hegde | S19: Not Synced | T19: 2026-07-13T16:47:47.687Z
A20: ADJ-0050 | B20: 13/07/2026 | C20: 0.94791667 | D20: ACH-MF-RM-0008 | E20: Micro Cover Glass Square No:1 22x22mm (pkt of 10 GMS) | F20: MF | G20: No | H20: MFG Store | I20: Inward | J20: 20 | K20: +Add | M20: For the cartridge well cover | N20: Sudarshan | P20: Siddharth R | Q20: Pending | S20: Not Synced | T20: 2026-07-13T17:15:27.185Z | U20: No Expiry
A21: ADJ-0052 | B21: 14/07/2026 | C21: 0.50416667 | D21: ACH-MF-CM-0063 | E21: Nitrogen - UHP | F21: MF | H21: Ambient Store | I21: Inward | J21: 3 | K21: +Add | M21: Nitrogen cylinders for MFG | N21: Nikihil | P21: Siddharth R | Q21: Pending | S21: Not Synced | T21: 2026-07-14T06:36:47.114Z | U21: No Expiry
A22: ADJ-0054 | B22: 14/07/2026 | C22: 0.52083333 | D22: ACH-MF-CT-0090 | E22: BFR10D6012X300X - Blood Separation Membrane Type: FR-1(0.6), Size: 12x300mm | F22: MF | G22: pcs | H22: General Store | I22: Inward | J22: 300 | K22: +Add | M22: Blood Separation Membrane (LFA) | N22: KOMAL NAVIN BHANUSHALI | P22: Siddharth R | Q22: Pending | S22: Not Synced | T22: 2026-07-14T07:00:48.411Z | U22: 46582
A23: ADJ-0056 | B23: 24/07/2026 | C23: 0.50763889 | D23: ACH-RD-CM-0094 | E23: Liquid Nitrogen | F23: RD | G23: Ltr | H23: MFG Store | I23: Inward | J23: 10 | K23: +Add | M23: Liquid nitrogen | N23: Nikhil Mane | P23: Shiva Raj | Q23: Logged | S23: Not Synced | T23: 2026-07-24T06:41:58.198Z | U23: No Expiry
A24: ADJ-0001 | B24: 27/07/2026 | C24: 0.6625 | D24: ACH-MF-CM-0002 | E24: Gloves Medium | F24: MF | H24: General Store | I24: Issue | J24: 1 | K24: -Deduct | M24: For Manufacturing | N24: SIDDHARTH | O24: RPT | P24: Shiva Raj | Q24: Logged | S24: Not Synced | T24: 2026-07-27T10:24:49.338Z

Sheet 4. Config
A1: ACHIRA LABS — CONFIGURATION & DROPDOWN LISTS (Admin Use Only)
A3: ADJUSTMENT TYPES | C3: EFFECT | E3: STATUS | G3: TALLY SYNC | I3: WAREHOUSE / LOCATION | K3: STORE MANAGERS
A4: Inward | C4: +Add | E4: Pending | G4: Not Synced | I4: 2-8 Fridge R_D Section | K4: Store Manager 1
A5: Damage | C5: -Deduct | E5: Approved | G5: Synced | I5: MFG Store | K5: Store Manager 2
A6: Return | E6: Rejected | G6: Sync Error | I6: Engineering Store | K6: Store Manager 3
A7: Recount | I7: General Store | K7: (Add names here)
A8: Transfer In | I8: Cold Room
A9: Transfer Out | I9: Ambient Store
A10: Write-Off | I10: QC Store
I11: Quarantine Area
A14: ARN DEPARTMENT & SUB-CATEGORY REFERENCE
A15: Dept | B15: Sub-Cat | C15: Full Code | D15: Description
A16: RD | B16: AB | C16: ACH-RD-AB | D16: Antibodies & Antigens
A17: RD | B17: CH | C17: ACH-RD-CH | D17: Chemicals & Reagents
A18: RD | B18: FL | C18: ACH-RD-FL | D18: Fluorophores & Bioconjugates
A19: RD | B19: BG | C19: ACH-RD-BG | D19: Biologics & Standards
A20: RD | B20: CM | C20: ACH-RD-CM | D20: R&D Consumables
A21: RD | B21: KT | C21: ACH-RD-KT | D21: Kits & Controls
A22: MF | B22: RM | C22: ACH-MF-RM | D22: Raw Materials
A23: MF | B23: CT | C23: ACH-MF-CT | D23: Cartridge Parts
A24: MF | B24: PM | C24: ACH-MF-PM | D24: Packaging Materials
A25: MF | B25: LB | C25: ACH-MF-LB | D25: Labels & Stickers
A26: MF | B26: CM | C26: ACH-MF-CM | D26: MFG Consumables
... A37: GN | B37: SF | C37: ACH-GN-SF | D37: Safety

Sheet 5. Dashboard
A1: ACHIRA LABS — INVENTORY DASHBOARD
A2: Last refreshed from Zoho: July 2026 | Total items: 3,414 | Active: 3,412 | Inactive: 2
A4: Total Items | C4: Active Items | E4: Inactive Items | G4: RD Items | I4: MFG Items | K4: ENG Items
A5: 3414 | C5: 3412 | E5: 2 | G5: 1727 | I5: 331 | K5: 1130
A8: ITEMS BY DEPARTMENT & SUB-CATEGORY
A9: Code | B9: Sub-Category | C9: Total | D9: Active
A10: ACH-EN-EL | B10: Electronics & PCBs | C10: 370 | D10: 370
A11: ACH-EN-EQ | B11: Equipment & Instruments | C11: 272 | D11: 272
A12: ACH-EN-ME | B12: Mechanical Parts | C12: 395 | D12: 395
A13: ACH-EN-OP | B13: Optical Components | C13: 34 | D13: 34
A14: ACH-EN-SP | B14: Software & Services | C14: 59 | D14: 59
A15: ACH-GN-FA | B15: Facilities | C15: 22 | D15: 22
A16: ACH-GN-HK | B16: Housekeeping & Canteen | C16: 49 | D16: 49
A17: ACH-GN-IT | B17: IT & Peripherals | C17: 107 | D17: 107
A18: ACH-GN-OF | B18: Office Supplies | C18: 23 | D18: 23
A19: ACH-GN-SF | B19: Safety | C19: 25 | D19: 25
A20: ACH-MF-CM | B20: Consumables | C20: 163 | D20: 163
A21: ACH-MF-CT | B21: Cartridge Parts | C21: 94 | D21: 94
... A31: ACH-RD-KT | B31: Kits & Controls | C31: 49 | D31: 49
